{
  "persons": [
    {
      "name": "Ada Lovelace",
      "number": "39-44-5323523",
      "id": 2
    },
    {
      "name": "Dan Abramov",
      "number": "12-43-234345",
      "id": 3
    },
    {
      "name": "Mary Poppendieck",
      "number": "39-23-6423122",
      "id": 4
    },
    {
      "name": "matti putkonen",
      "number": "0449586954",
      "id": 5
    },
    {
      "name": "pertti mikkola",
      "number": "0500123",
      "id": 6
    },
    {
      "name": "mikko mikkonen",
      "number": "040293403",
      "id": 55
    },
    {
      "name": "matti mattinen",
      "number": "0406578453",
      "id": 98
    }
  ]
}